{
  "title": "Cooling Centers and Spaces",
  "url": "https://services7.arcgis.com/YGmp70c76pih9ea2/arcgis/rest/services/City_of_Medical_Lake_Cooling_Resources_Map/FeatureServer/0",
  "features": [
    {
      "attributes": {
        "OBJECTID": 1,
        "Name": "Medical Lake Library",
        "Type_of_Center": "Library",
        "Address": "321 E Herb St, Medical Lake, WA 99022",
        "Hours": "(509) 893-8330",
        "Street_Address": "321 E Herb St",
        "City": " Medical Lake",
        "State": "WA",
        "Zip_Code": "99022"
      },
      "geometry": {
        "x": -117.67776936184598,
        "y": 47.57151339827689
      }
    }
  ]
}